LICENSE
MANIFEST.in
README.rst
setup.py
xmlrpc2/__init__.py
xmlrpc2/client.py
xmlrpc2/exceptions.py
xmlrpc2/requests.py
xmlrpc2/serializer.py
xmlrpc2.egg-info/PKG-INFO
xmlrpc2.egg-info/SOURCES.txt
xmlrpc2.egg-info/dependency_links.txt
xmlrpc2.egg-info/not-zip-safe
xmlrpc2.egg-info/requires.txt
xmlrpc2.egg-info/top_level.txt