Metadata-Version: 1.0
Name: xmlrpc2
Version: 0.2.1
Summary: UNKNOWN
Home-page: https://github.com/dstufft/xmlrpc2
Author: Donald Stufft
Author-email: donald.stufft@gmail.com
License: Copyright (c) Donald Stufft
